CLA/cla.v
module cla(a,b,cin,sum,cout);
	input a,b,cin;
	output sum,cout;

	assign cout = (a&b)|((a|b)&cin);
	assign sum = a^b^cin;

endmodule

CLA/dump.vcd
$version Generated by VerilatedVcd $end
$timescale 1s $end

 $scope module TOP $end
  $var wire  1 # a $end
  $var wire  1 $ b $end
  $var wire  1 % cin $end
  $var wire  1 ' cout $end
  $var wire  1 & sum $end
  $scope module cla $end
   $var wire  1 # a $end
   $var wire  1 $ b $end
   $var wire  1 % cin $end
   $var wire  1 ' cout $end
   $var wire  1 & sum $end
  $upscope $end
 $upscope $end
$enddefinitions $end


#1
0#
0$
0%
0&
0'
#2
1$
1&
#3
1#
0$
#4
1$
0&
1'
#5
0#
0$
1%
1&
0'
#6
1$
0&
1'
#7
1#
0$
#8
1$
1&
